{
  "name": "Catherine Kim",
  "lastName": "Kim",
  "credentials": "DO",
  "title": "Attending Physician",
  "locations": [
    "West"
  ],
  "image": "/images/providers/kim-catherine.jpg",
  "bio": "Dr. Kim received her medical degree from the Philadelphia College of Osteopathic Medicine. She completed her Internal Medicine residency at the University of Florida, followed by a fellowship in Pulmonary and Critical Care Medicine at Virginia Commonwealth University. In her free time, she enjoys running, baking, and traveling.",
  "categories": [
    "critical-care",
    "outpatient-pulmonary-sleep"
  ],
  "education": "Philadelphia College of Osteopathic Medicine Georgia Campus",
  "residency": "University of Florida",
  "fellowship": "Virginia Commonwealth University"
}
